setup.py
newslynx_url/__init__.py
newslynx_url/regex.py
newslynx_url/tools.py
newslynx_url.egg-info/PKG-INFO
newslynx_url.egg-info/SOURCES.txt
newslynx_url.egg-info/dependency_links.txt
newslynx_url.egg-info/namespace_packages.txt
newslynx_url.egg-info/not-zip-safe
newslynx_url.egg-info/requires.txt
newslynx_url.egg-info/top_level.txt