Metadata-Version: 1.1
Name: newslynx-url
Version: 0.1.0
Summary: Tools for parsing, extracting, reconciling, and unshortening urls
Home-page: http://github.com/newslynx/newslynx-urls
Author: Brian Abelson
Author-email: brian@newslynx.org
License: MIT
Keywords: urls
Platform: UNKNOWN
Classifier: Development Status :: 3 - Alpha
Classifier: Intended Audience :: Developers
Classifier: License :: OSI Approved :: MIT License
Classifier: Operating System :: OS Independent
Classifier: Programming Language :: Python
